hs110_exporter/__init__.py
hs110_exporter/collector.py
hs110_exporter/http.py
hs110_exporter-0.0.1.data/scripts/hs110_exporter
hs110_exporter-0.0.1.dist-info/LICENSE
hs110_exporter-0.0.1.dist-info/METADATA
hs110_exporter-0.0.1.dist-info/WHEEL
hs110_exporter-0.0.1.dist-info/top_level.txt
hs110_exporter-0.0.1.dist-info/RECORD
